exdown/__about__.py
exdown/__init__.py
exdown/main.py
exdown-0.5.0.dist-info/LICENSE.txt
exdown-0.5.0.dist-info/METADATA
exdown-0.5.0.dist-info/WHEEL
exdown-0.5.0.dist-info/top_level.txt
exdown-0.5.0.dist-info/RECORD
