Metadata-Version: 2.1
Name: exdown
Version: 0.5.0
Summary: Extract code blocks from markdown
Home-page: https://github.com/nschloe/exdown
Author: Nico Schlömer
Author-email: nico.schloemer@gmail.com
License: MIT
Project-URL: Code, https://github.com/nschloe/exdown
Project-URL: Issues, https://github.com/nschloe/exdown/issues
Platform: UNKNOWN
Classifier: Development Status :: 4 - Beta
Classifier: Intended Audience :: Developers
Classifier: License :: OSI Approved :: MIT License
Classifier: Operating System :: OS Independent
Classifier: Programming Language :: Python
Classifier: Programming Language :: Python :: 3
Classifier: Programming Language :: Python :: 3.6
Classifier: Programming Language :: Python :: 3.7
Classifier: Programming Language :: Python :: 3.8
Classifier: Topic :: Text Processing
Requires-Python: >=3.6
License-File: LICENSE.txt
Requires-Dist: importlib-metadata ; python_version < "3.8"
